{
  "openapi": "3.0.0",
  "info": {
    "title": "Elite Desi Farms API",
    "version": "1.0.0",
    "description": "API documentation for Elite Desi Farms backend"
  },
  "servers": [
    {
      "url": "http://localhost:5000"
    }
  ],
  "paths": {
    "/api/products": {
      "get": {
        "summary": "Get all products",
        "responses": {
          "200": {
            "description": "List of products"
          }
        }
      },
      "post": {
        "summary": "Create a new product",
        "requestBody": {
          "required": true,
          "content": {
            "application/json": {
              "schema": {
                "type": "object",
                "properties": {
                  "name": { "type": "string" },
                  "category": { "type": "string" },
                  "type": { "type": "string" },
                  "price": { "type": "number" },
                  "stock": { "type": "number" },
                  "image": { "type": "string" }
                }
              }
            }
          }
        },
        "responses": {
          "201": {
            "description": "Product created successfully"
          }
        }
      }
    }
  }
}
